{
  "formatVersion": 1,
  "database": {
    "version": 2,
    "identityHash": "f4b7351cb50ee438e01e96de36aa1140",
    "entities": [
      {
        "tableName": "draft",
        "createSql": "CREATE TABLE IF NOT EXISTS `${TABLE_NAME}` (`imagePath` TEXT NOT NULL, `merchantName` TEXT, `date` INTEGER, `total` REAL, `currency` TEXT, `isLinked` INTEGER NOT NULL, `creationTimestamp` INTEGER NOT NULL, `id` INTEGER PRIMARY KEY AUTOINCREMENT)",
        "fields": [
          {
            "fieldPath": "imagePath",
            "columnName": "imagePath",
            "affinity": "TEXT",
            "notNull": true
          },
          {
            "fieldPath": "merchantName",
            "columnName": "merchantName",
            "affinity": "TEXT",
            "notNull": false
          },
          {
            "fieldPath": "date",
            "columnName": "date",
            "affinity": "INTEGER",
            "notNull": false
          },
          {
            "fieldPath": "total",
            "columnName": "total",
            "affinity": "REAL",
            "notNull": false
          },
          {
            "fieldPath": "currency",
            "columnName": "currency",
            "affinity": "TEXT",
            "notNull": false
          },
          {
            "fieldPath": "isLinked",
            "columnName": "isLinked",
            "affinity": "INTEGER",
            "notNull": true
          },
          {
            "fieldPath": "creationTimestamp",
            "columnName": "creationTimestamp",
            "affinity": "INTEGER",
            "notNull": true
          },
          {
            "fieldPath": "id",
            "columnName": "id",
            "affinity": "INTEGER",
            "notNull": false
          }
        ],
        "primaryKey": {
          "columnNames": [
            "id"
          ],
          "autoGenerate": true
        },
        "indices": [],
        "foreignKeys": []
      },
      {
        "tableName": "annotation",
        "createSql": "CREATE TABLE IF NOT EXISTS `${TABLE_NAME}` (`text` TEXT NOT NULL, `top` INTEGER NOT NULL, `bottom` INTEGER NOT NULL, `left` INTEGER NOT NULL, `right` INTEGER NOT NULL, `tag` INTEGER NOT NULL, `id` INTEGER PRIMARY KEY AUTOINCREMENT, `draftId` INTEGER, FOREIGN KEY(`draftId`) REFERENCES `draft`(`id`) ON UPDATE NO ACTION ON DELETE CASCADE )",
        "fields": [
          {
            "fieldPath": "text",
            "columnName": "text",
            "affinity": "TEXT",
            "notNull": true
          },
          {
            "fieldPath": "top",
            "columnName": "top",
            "affinity": "INTEGER",
            "notNull": true
          },
          {
            "fieldPath": "bottom",
            "columnName": "bottom",
            "affinity": "INTEGER",
            "notNull": true
          },
          {
            "fieldPath": "left",
            "columnName": "left",
            "affinity": "INTEGER",
            "notNull": true
          },
          {
            "fieldPath": "right",
            "columnName": "right",
            "affinity": "INTEGER",
            "notNull": true
          },
          {
            "fieldPath": "tag",
            "columnName": "tag",
            "affinity": "INTEGER",
            "notNull": true
          },
          {
            "fieldPath": "id",
            "columnName": "id",
            "affinity": "INTEGER",
            "notNull": false
          },
          {
            "fieldPath": "draftId",
            "columnName": "draftId",
            "affinity": "INTEGER",
            "notNull": false
          }
        ],
        "primaryKey": {
          "columnNames": [
            "id"
          ],
          "autoGenerate": true
        },
        "indices": [
          {
            "name": "index_annotation_draftId",
            "unique": false,
            "columnNames": [
              "draftId"
            ],
            "createSql": "CREATE  INDEX `index_annotation_draftId` ON `${TABLE_NAME}` (`draftId`)"
          }
        ],
        "foreignKeys": [
          {
            "table": "draft",
            "onDelete": "CASCADE",
            "onUpdate": "NO ACTION",
            "columns": [
              "draftId"
            ],
            "referencedColumns": [
              "id"
            ]
          }
        ]
      },
      {
        "tableName": "productDraft",
        "createSql": "CREATE TABLE IF NOT EXISTS `${TABLE_NAME}` (`name` TEXT NOT NULL, `price` REAL NOT NULL, `id` INTEGER PRIMARY KEY AUTOINCREMENT, `draftId` INTEGER, FOREIGN KEY(`draftId`) REFERENCES `draft`(`id`) ON UPDATE NO ACTION ON DELETE CASCADE )",
        "fields": [
          {
            "fieldPath": "name",
            "columnName": "name",
            "affinity": "TEXT",
            "notNull": true
          },
          {
            "fieldPath": "price",
            "columnName": "price",
            "affinity": "REAL",
            "notNull": true
          },
          {
            "fieldPath": "id",
            "columnName": "id",
            "affinity": "INTEGER",
            "notNull": false
          },
          {
            "fieldPath": "draftId",
            "columnName": "draftId",
            "affinity": "INTEGER",
            "notNull": false
          }
        ],
        "primaryKey": {
          "columnNames": [
            "id"
          ],
          "autoGenerate": true
        },
        "indices": [
          {
            "name": "index_productDraft_draftId",
            "unique": false,
            "columnNames": [
              "draftId"
            ],
            "createSql": "CREATE  INDEX `index_productDraft_draftId` ON `${TABLE_NAME}` (`draftId`)"
          }
        ],
        "foreignKeys": [
          {
            "table": "draft",
            "onDelete": "CASCADE",
            "onUpdate": "NO ACTION",
            "columns": [
              "draftId"
            ],
            "referencedColumns": [
              "id"
            ]
          }
        ]
      }
    ],
    "views": [],
    "setupQueries": [
      "CREATE TABLE IF NOT EXISTS room_master_table (id INTEGER PRIMARY KEY,identity_hash TEXT)",
      "INSERT OR REPLACE INTO room_master_table (id,identity_hash) VALUES(42, 'f4b7351cb50ee438e01e96de36aa1140')"
    ]
  }
}